dev/test_hola_mundo.py
dev_python-0.1.0.dist-info/METADATA
dev_python-0.1.0.dist-info/WHEEL
dev_python-0.1.0.dist-info/RECORD
