Metadata-Version: 2.1
Name: dev-python
Version: 0.1.0
Summary: mindmap dev
Author: luis salamo
Author-email: lsalamo@gmail.com
Requires-Python: >=3.12,<4.0
Classifier: Programming Language :: Python :: 3
Classifier: Programming Language :: Python :: 3.12
